tr_lang_py-0.2.0.dist-info/METADATA
tr_lang_py-0.2.0.dist-info/WHEEL
tr_lang/__init__.py
tr_lang/tr_lang.cpython-38-x86_64-linux-gnu.so
tr_lang_py-0.2.0.dist-info/RECORD
