Metadata-Version: 2.1
Name: tr-lang-py
Version: 0.2.0
